[
    {
        "title" : "What is Chrismas?",
        "sub_title" : "Chrismas คือ การฉลองวันประสูติของพระเยซูผู้เป็นศาสดาสูงสุดของชาวคริสต์ทั่วโลก เป็นวันฉลองที่มีความสำคัญ และมีความหมายมากที่สุดวันหนึ่ง",
        "image_url" : "https://cdn.pixabay.com/photo/2016/11/14/09/14/cat-1822979_960_720.jpg",
        "detail" : "คริสต์มาส เป็นคำทับศัพท์ภาษาอังกฤษ Christmas ซึ่งมาจากภาษาอังกฤษ โบราณว่า Christes Maesse ที่แปลว่า บูชามิสซาของพระคริสตเจ้า เพราะการร่วมพิธีมิสซาเป็นประเพณีสำคัญที่สุดที่ชาวคริสต์ ถือปฎิบัติกันในวันคริสต์มาส"
    },

    {
        "title" : "What date is Chrismas?",
        "sub_title" : "25 ธันวาคม",
        "image_url" : "https://cdn.pixabay.com/photo/2016/11/14/16/20/snowflake-1823942_960_720.jpg",
        "detail" : "Christmas คือ วันที่ 25 ธันวาคมของทุกปี ตามระบบปฏิทินสมัยใหม่"
    },

    {
        "title" : "What is Chrismas Eve?",
        "sub_title" : "Christmas Eve คือ วันที่ 24 ธันวาคมของทุกปี ตามระบบปฏิทินสมัยใหม่ ",
        "image_url" : "https://cdn.pixabay.com/photo/2016/11/29/13/37/christmas-1869902_960_720.jpg",
        "detail" : "Christmas Eve คือ เย็นแรกของวันคริสต์มาส ซึ่งมีการเฉลิมฉลองเพื่อระลึกถึง การประสูติของพระเยซู"
    },

    {
        "title" : "เรื่องเล่าจากซานตาครอส",
        "sub_title" : "ตัวจริงของซานตาครอส คือ นักบุญนิโคลัสซึ่งเป็นบาทหลวงในตุรกี ช่วงคริสต์ศตวรรษที่สี่ ผู้ขึ้นชื่อในเรื่องความใจดี โดยเฉพาะกับเด็กๆ",
        "image_url" : "https://s.isanook.com/ca/0/rp/r/w728/ya0xa0m1w0/aHR0cHM6Ly9zLmlzYW5vb2suY29tL2NhLzAvdWQvMTg4Lzk0NDMzOS9jaHJpc3RtYXMuanBn.jpg",
        "detail" : "ภาพของซานตาคลอสเป็นชายร่างผอมสูงสวมชุดสีเขียว หรือน้ำตาลสลับแดง เจนนี ไนสตรอม ศิลปินชาวสวีเดน เป็นผู้คิดค้นรูปลักษณ์ของซานตาครอสอย่างที่เห็นกันในปัจจุบัน โดยวาดภาพลงในบัตรอวยพรคริสต์มาส ภาพเหล่านี้ได้รับความนิยมไปทั่วโลก เมื่อชาวสวีเดนอีกคนชื่อ แฮดดอน ซันด์บลอม นำภาพวาดของไนสตรอมสวมชุดขาว"
    }
]